django_http_referrer_policy/__init__.py
django_http_referrer_policy/apps.py
django_http_referrer_policy/middleware.py
django_http_referrer_policy-1.1.1.dist-info/AUTHORS.rst
django_http_referrer_policy-1.1.1.dist-info/LICENSE
django_http_referrer_policy-1.1.1.dist-info/METADATA
django_http_referrer_policy-1.1.1.dist-info/WHEEL
django_http_referrer_policy-1.1.1.dist-info/top_level.txt
django_http_referrer_policy-1.1.1.dist-info/RECORD
