Metadata-Version: 2.1
Name: django-http-referrer-policy
Version: 1.1.1
Summary: django-http-referrer-policy provides a middleware class implementing the Referrer-Policy header for Django-powered sites.
Home-page: https://django-http-referrer-policy.readthedocs.io/
Author: Dmytro Litvinov
Author-email: me@DmytroLitvinov.com
License: MIT
Project-URL: Bug Reports, https://github.com/DmytroLitvinov/django-http-referrer-policy/issues
Project-URL: Source, https://github.com/DmytroLitvinov/django-http-referrer-policy
Keywords: django-http-referrer-policy django http-referrer
Platform: UNKNOWN
Classifier: Development Status :: 5 - Production/Stable
Classifier: Framework :: Django :: 1.11
Classifier: Framework :: Django :: 2.1
Classifier: Framework :: Django :: 2.2
Classifier: Framework :: Django :: 3.0
Classifier: Framework :: Django :: 3.1
Classifier: Intended Audience :: Developers
Classifier: License :: OSI Approved :: BSD License
Classifier: Natural Language :: English
Classifier: Programming Language :: Python :: 3
Classifier: Programming Language :: Python :: 3.5
Classifier: Programming Language :: Python :: 3.6
Classifier: Programming Language :: Python :: 3.7
Classifier: Programming Language :: Python :: 3.8
Classifier: Programming Language :: Python :: 3.9
Requires-Python: >=3.5.0
Requires-Dist: Django (>=1.11)
